vncuda/CTPMarket.py
vncuda/CTPMarketType.py
vncuda/__init__.py
vncuda/globalType.py
vncuda/globalvar.py
vncuda/main.py
vnta-1.0.dist-info/LICENSE
vnta-1.0.dist-info/METADATA
vnta-1.0.dist-info/WHEEL
vnta-1.0.dist-info/top_level.txt
vnta-1.0.dist-info/RECORD
